dslibs/__init__.py
dslibs_baosws-0.0.1.dist-info/LICENSE
dslibs_baosws-0.0.1.dist-info/METADATA
dslibs_baosws-0.0.1.dist-info/WHEEL
dslibs_baosws-0.0.1.dist-info/top_level.txt
dslibs_baosws-0.0.1.dist-info/RECORD
