Metadata-Version: 2.1
Name: dslibs-baosws
Version: 0.0.1
Summary: A unified module of frequently used data-science modules
Home-page: https://github.com/baosws/dslibs/
Author: Example Author
Author-email: baosws@gmail.com
License: UNKNOWN
Platform: UNKNOWN
Classifier: Programming Language :: Python :: 3
Classifier: License :: OSI Approved :: MIT License
Classifier: Operating System :: OS Independent
Requires-Python: >=3.6
Requires-Dist: pandas
Requires-Dist: scikit-learn
Requires-Dist: matplotlib
Requires-Dist: numpy
Requires-Dist: statsmodels
Requires-Dist: scipy
Requires-Dist: seaborn
